edumud/__init__.py
edumud/cells.py
edumud/colloids.py
edumud/constants.py
edumud/electrolytes.py
edumud/file_utils.py
edumud/particles.py
edumud-0.0.8.dist-info/LICENSE
edumud-0.0.8.dist-info/METADATA
edumud-0.0.8.dist-info/WHEEL
edumud-0.0.8.dist-info/top_level.txt
edumud-0.0.8.dist-info/RECORD
