Metadata-Version: 2.1
Name: edumud
Version: 0.0.8
Summary: Educational MUDNET software in Python
Author-email: "Paul J.M. van Kan" <p.j.m.vankan@tudelft.nl>
Project-URL: Homepage, https://bitbucket.org/deltares/edumud/
Classifier: Programming Language :: Python :: 3
Classifier: License :: OSI Approved :: GNU General Public License v3 or later (GPLv3+)
Classifier: Operating System :: OS Independent
Requires-Python: >=3.10
License-File: LICENSE
